inky_toolkit/__init__.py
inky_toolkit/inkytext.py
inky_toolkit_stezante7-0.1.0.dist-info/LICENCE
inky_toolkit_stezante7-0.1.0.dist-info/METADATA
inky_toolkit_stezante7-0.1.0.dist-info/WHEEL
inky_toolkit_stezante7-0.1.0.dist-info/top_level.txt
inky_toolkit_stezante7-0.1.0.dist-info/RECORD
