Metadata-Version: 2.1
Name: inky-toolkit-stezante7
Version: 0.1.0
Summary: Inky Toolkit
Home-page: https://github.com/stezante7/InkyToolkit-stezante7
Author: Stefano Zante
Author-email: stezante7@gmail.com
License: UNKNOWN
Platform: UNKNOWN
Classifier: Programming Language :: Python :: 3
Classifier: License :: OSI Approved :: MIT License
Classifier: Operating System :: OS Independent
